{
    "name": "48-N",
    "physical_luminance_range": [
        0.0,
        1.0
    ],
    "mean_luminance": 0.5,
    "sweeps": [
        {
            "key": 0.0,
            "trials": [
                {
                    "sf": 1.0,
                    "contrast_ratio": 0.2,
                    "duration": 12.863523100037128,
                    "success": true,
                    "additional_data": null
                },
                {
                    "sf": 1.333521432163324,
                    "contrast_ratio": 0.2,
                    "duration": 13.380631600040942,
                    "success": true,
                    "additional_data": null
                },
                {
                    "sf": 1.7782794100389228,
                    "contrast_ratio": 0.2,
                    "duration": 15.866493600071408,
                    "success": true,
                    "additional_data": null
                },
                {
                    "sf": 2.3713737056616555,
                    "contrast_ratio": 0.2,
                    "duration": 16.88427280005999,
                    "success": true,
                    "additional_data": null
                },
                {
                    "sf": 3.16227766016838,
                    "contrast_ratio": 0.2,
                    "duration": 17.56784700008575,
                    "success": true,
                    "additional_data": null
                },
                {
                    "sf": 4.216965034285824,
                    "contrast_ratio": 0.2,
                    "duration": 18.218410800094716,
                    "success": true,
                    "additional_data": null
                },
                {
                    "sf": 5.623413251903492,
                    "contrast_ratio": 0.2,
                    "duration": 19.820493300096132,
                    "success": true,
                    "additional_data": null
                },
                {
                    "sf": 7.49894209332456,
                    "contrast_ratio": 0.2,
                    "duration": 20.403951700078323,
                    "success": true,
                    "additional_data": null
                },
                {
                    "sf": 10.000000000000004,
                    "contrast_ratio": 0.2,
                    "duration": 20.821248200023547,
                    "success": true,
                    "additional_data": null
                },
                {
                    "sf": 13.335214321633243,
                    "contrast_ratio": 0.2,
                    "duration": 57.04094860004261,
                    "success": false,
                    "additional_data": null
                }
            ]
        },
        {
            "key": 80.06502789702235,
            "trials": [
                {
                    "sf": 1.0,
                    "contrast_ratio": 0.2,
                    "duration": 23.023574899998493,
                    "success": true,
                    "additional_data": null
                },
                {
                    "sf": 1.0509118634687664,
                    "contrast_ratio": 0.13445930159883876,
                    "duration": 23.440439700032584,
                    "success": true,
                    "additional_data": null
                },
                {
                    "sf": 1.1044157447793956,
                    "contrast_ratio": 0.0903965189322374,
                    "duration": 24.20821780001279,
                    "success": true,
                    "additional_data": null
                },
                {
                    "sf": 1.1606436083903604,
                    "contrast_ratio": 0.06077326401297422,
                    "duration": 25.175693900091574,
                    "success": true,
                    "additional_data": null
                },
                {
                    "sf": 1.219734137316627,
                    "contrast_ratio": 0.04085765317533177,
                    "duration": 25.742911600042135,
                    "success": true,
                    "additional_data": null
                },
                {
                    "sf": 1.281833075183885,
                    "contrast_ratio": 0.027468457554613437,
                    "duration": 26.29363780003041,
                    "success": true,
                    "additional_data": null
                },
                {
                    "sf": 1.3470935856973965,
                    "contrast_ratio": 0.018466948093953335,
                    "duration": 26.81051900004968,
                    "success": true,
                    "additional_data": null
                },
                {
                    "sf": 1.4156766304120734,
                    "contrast_ratio": 0.012415264716874862,
                    "duration": 27.978612400009297,
                    "success": true,
                    "additional_data": null
                },
                {
                    "sf": 1.4877513657355363,
                    "contrast_ratio": 0.00834673911497849,
                    "duration": 57.04094860004261,
                    "success": false,
                    "additional_data": null
                }
            ]
        },
        {
            "key": 106.75337052936312,
            "trials": [
                {
                    "sf": 1.0,
                    "contrast_ratio": 0.2,
                    "duration": 37.20429050002713,
                    "success": true,
                    "additional_data": null
                },
                {
                    "sf": 0.9203826540957304,
                    "contrast_ratio": 0.1359553594389355,
                    "duration": 37.98854340007529,
                    "success": true,
                    "additional_data": null
                },
                {
                    "sf": 0.8471042299603007,
                    "contrast_ratio": 0.09241929880085073,
                    "duration": 38.87262969999574,
                    "success": true,
                    "additional_data": null
                },
                {
                    "sf": 0.7796600394665815,
                    "contrast_ratio": 0.06282449493782019,
                    "duration": 40.17393220006488,
                    "success": true,
                    "additional_data": null
                },
                {
                    "sf": 0.7175855764166341,
                    "contrast_ratio": 0.04270663395420465,
                    "duration": 40.94128410005942,
                    "success": true,
                    "additional_data": null
                },
                {
                    "sf": 0.6604533173631563,
                    "contrast_ratio": 0.029030978848354694,
                    "duration": 41.5753709001001,
                    "success": true,
                    "additional_data": null
                },
                {
                    "sf": 0.6078697771410314,
                    "contrast_ratio": 0.019734585820960972,
                    "duration": 43.84446739999112,
                    "success": true,
                    "additional_data": null
                },
                {
                    "sf": 0.5594727988296426,
                    "contrast_ratio": 0.013415113543336344,
                    "duration": 45.4794353999896,
                    "success": true,
                    "additional_data": null
                },
                {
                    "sf": 0.514929059481193,
                    "contrast_ratio": 0.009119282918492124,
                    "duration": 47.71489639999345,
                    "success": true,
                    "additional_data": null
                },
                {
                    "sf": 0.4739317744363186,
                    "contrast_ratio": 0.006199076935044706,
                    "duration": 57.04094860004261,
                    "success": false,
                    "additional_data": null
                }
            ]
        },
        {
            "key": 26.68834263234078,
            "trials": [
                {
                    "sf": 1.0,
                    "contrast_ratio": 0.2,
                    "duration": 29.997064199997112,
                    "success": true,
                    "additional_data": null
                },
                {
                    "sf": 1.2932510762519365,
                    "contrast_ratio": 0.1668791458840997,
                    "duration": 31.64902280003298,
                    "success": true,
                    "additional_data": null
                },
                {
                    "sf": 1.672498346226792,
                    "contrast_ratio": 0.13924324665503315,
                    "duration": 32.749849800020456,
                    "success": true,
                    "additional_data": null
                },
                {
                    "sf": 2.1629602862873822,
                    "contrast_ratio": 0.11618397035960476,
                    "duration": 33.16688230005093,
                    "success": true,
                    "additional_data": null
                },
                {
                    "sf": 2.7972507181313544,
                    "contrast_ratio": 0.09694340869517198,
                    "duration": 34.45161350001581,
                    "success": true,
                    "additional_data": null
                },
                {
                    "sf": 3.617547501769875,
                    "contrast_ratio": 0.08088916621071751,
                    "duration": 35.10249050008133,
                    "success": true,
                    "additional_data": null
                },
                {
                    "sf": 4.678397200056396,
                    "contrast_ratio": 0.06749357484260758,
                    "duration": 35.80290170002263,
                    "success": true,
                    "additional_data": null
                },
                {
                    "sf": 6.050342214106982,
                    "contrast_ratio": 0.05631635061199455,
                    "duration": 57.04094860004261,
                    "success": false,
                    "additional_data": null
                }
            ]
        },
        {
            "key": 53.37668526468156,
            "trials": [
                {
                    "sf": 1.0,
                    "contrast_ratio": 0.2,
                    "duration": 3.787607000092976,
                    "success": true,
                    "additional_data": null
                },
                {
                    "sf": 1.1873231576444914,
                    "contrast_ratio": 0.1447197292187059,
                    "duration": 4.2046089000068605,
                    "success": true,
                    "additional_data": null
                },
                {
                    "sf": 1.409736280678886,
                    "contrast_ratio": 0.10471900012567781,
                    "duration": 6.807256100000814,
                    "success": true,
                    "additional_data": null
                },
                {
                    "sf": 1.673812532221656,
                    "contrast_ratio": 0.07577452671120863,
                    "duration": 7.941771500045434,
                    "success": true,
                    "additional_data": null
                },
                {
                    "sf": 1.9873563810623387,
                    "contrast_ratio": 0.054830344936608544,
                    "duration": 9.143070099991746,
                    "success": true,
                    "additional_data": null
                },
                {
                    "sf": 2.3596342537278647,
                    "contrast_ratio": 0.03967516336097116,
                    "duration": 9.593631000025198,
                    "success": true,
                    "additional_data": null
                },
                {
                    "sf": 2.8016483930222713,
                    "contrast_ratio": 0.028708894491538347,
                    "duration": 10.51090940006543,
                    "success": true,
                    "additional_data": null
                },
                {
                    "sf": 3.3264620166128185,
                    "contrast_ratio": 0.020773717184919133,
                    "duration": 57.04094860004261,
                    "success": false,
                    "additional_data": null
                }
            ]
        },
        {
            "key": 0.0,
            "trials": [
                {
                    "sf": 1.0,
                    "contrast_ratio": 0.2,
                    "duration": 23.373112399945967,
                    "success": true,
                    "additional_data": null
                },
                {
                    "sf": 1.333521432163324,
                    "contrast_ratio": 0.2,
                    "duration": 24.49115180002991,
                    "success": true,
                    "additional_data": null
                },
                {
                    "sf": 1.7782794100389228,
                    "contrast_ratio": 0.2,
                    "duration": 25.258558099973015,
                    "success": true,
                    "additional_data": null
                },
                {
                    "sf": 2.3713737056616555,
                    "contrast_ratio": 0.2,
                    "duration": 25.675720200059004,
                    "success": true,
                    "additional_data": null
                },
                {
                    "sf": 3.16227766016838,
                    "contrast_ratio": 0.2,
                    "duration": 26.14279890002217,
                    "success": true,
                    "additional_data": null
                },
                {
                    "sf": 4.216965034285824,
                    "contrast_ratio": 0.2,
                    "duration": 27.827582799945958,
                    "success": true,
                    "additional_data": null
                },
                {
                    "sf": 5.623413251903492,
                    "contrast_ratio": 0.2,
                    "duration": 29.06236760003958,
                    "success": true,
                    "additional_data": null
                },
                {
                    "sf": 7.49894209332456,
                    "contrast_ratio": 0.2,
                    "duration": 29.64611790003255,
                    "success": true,
                    "additional_data": null
                },
                {
                    "sf": 10.000000000000004,
                    "contrast_ratio": 0.2,
                    "duration": 31.497915199957788,
                    "success": true,
                    "additional_data": null
                },
                {
                    "sf": 13.335214321633243,
                    "contrast_ratio": 0.2,
                    "duration": 64.81460120005067,
                    "success": false,
                    "additional_data": null
                }
            ]
        },
        {
            "key": 106.75337052936312,
            "trials": [
                {
                    "sf": 1.0,
                    "contrast_ratio": 0.2,
                    "duration": 33.81685890001245,
                    "success": true,
                    "additional_data": null
                },
                {
                    "sf": 0.9203826540957304,
                    "contrast_ratio": 0.1359553594389355,
                    "duration": 34.26730109995697,
                    "success": true,
                    "additional_data": null
                },
                {
                    "sf": 0.8471042299603007,
                    "contrast_ratio": 0.09241929880085073,
                    "duration": 35.35206189996097,
                    "success": true,
                    "additional_data": null
                },
                {
                    "sf": 0.7796600394665815,
                    "contrast_ratio": 0.06282449493782019,
                    "duration": 36.369734499952756,
                    "success": true,
                    "additional_data": null
                },
                {
                    "sf": 0.7175855764166341,
                    "contrast_ratio": 0.04270663395420465,
                    "duration": 39.289002100005746,
                    "success": true,
                    "additional_data": null
                },
                {
                    "sf": 0.6604533173631563,
                    "contrast_ratio": 0.029030978848354694,
                    "duration": 40.423817300004885,
                    "success": true,
                    "additional_data": null
                },
                {
                    "sf": 0.6078697771410314,
                    "contrast_ratio": 0.019734585820960972,
                    "duration": 43.393170900060795,
                    "success": true,
                    "additional_data": null
                },
                {
                    "sf": 0.5594727988296426,
                    "contrast_ratio": 0.013415113543336344,
                    "duration": 44.677780400030315,
                    "success": true,
                    "additional_data": null
                },
                {
                    "sf": 0.514929059481193,
                    "contrast_ratio": 0.009119282918492124,
                    "duration": 47.46396490000188,
                    "success": true,
                    "additional_data": null
                },
                {
                    "sf": 0.4739317744363186,
                    "contrast_ratio": 0.006199076935044706,
                    "duration": 64.81460120005067,
                    "success": false,
                    "additional_data": null
                }
            ]
        },
        {
            "key": 80.06502789702235,
            "trials": [
                {
                    "sf": 1.0,
                    "contrast_ratio": 0.2,
                    "duration": 14.481068299966864,
                    "success": true,
                    "additional_data": null
                },
                {
                    "sf": 1.0509118634687664,
                    "contrast_ratio": 0.13445930159883876,
                    "duration": 15.599012000020593,
                    "success": true,
                    "additional_data": null
                },
                {
                    "sf": 1.1044157447793956,
                    "contrast_ratio": 0.0903965189322374,
                    "duration": 16.11587540002074,
                    "success": true,
                    "additional_data": null
                },
                {
                    "sf": 1.1606436083903604,
                    "contrast_ratio": 0.06077326401297422,
                    "duration": 16.54986979998648,
                    "success": true,
                    "additional_data": null
                },
                {
                    "sf": 1.219734137316627,
                    "contrast_ratio": 0.04085765317533177,
                    "duration": 17.75109200004954,
                    "success": true,
                    "additional_data": null
                },
                {
                    "sf": 1.281833075183885,
                    "contrast_ratio": 0.027468457554613437,
                    "duration": 18.167969599948265,
                    "success": true,
                    "additional_data": null
                },
                {
                    "sf": 1.3470935856973965,
                    "contrast_ratio": 0.018466948093953335,
                    "duration": 19.78622390003875,
                    "success": true,
                    "additional_data": null
                },
                {
                    "sf": 1.4156766304120734,
                    "contrast_ratio": 0.012415264716874862,
                    "duration": 20.987718699965626,
                    "success": true,
                    "additional_data": null
                },
                {
                    "sf": 1.4877513657355363,
                    "contrast_ratio": 0.00834673911497849,
                    "duration": 21.521316200029105,
                    "success": true,
                    "additional_data": null
                },
                {
                    "sf": 1.5634955601433351,
                    "contrast_ratio": 0.005611483560138585,
                    "duration": 64.81460120005067,
                    "success": false,
                    "additional_data": null
                }
            ]
        },
        {
            "key": 26.68834263234078,
            "trials": [
                {
                    "sf": 1.0,
                    "contrast_ratio": 0.2,
                    "duration": 50.11661779996939,
                    "success": true,
                    "additional_data": null
                },
                {
                    "sf": 1.2932510762519365,
                    "contrast_ratio": 0.1668791458840997,
                    "duration": 50.88415439997334,
                    "success": true,
                    "additional_data": null
                },
                {
                    "sf": 1.672498346226792,
                    "contrast_ratio": 0.13924324665503315,
                    "duration": 52.41877290001139,
                    "success": true,
                    "additional_data": null
                },
                {
                    "sf": 2.1629602862873822,
                    "contrast_ratio": 0.11618397035960476,
                    "duration": 52.83609929995146,
                    "success": true,
                    "additional_data": null
                },
                {
                    "sf": 2.7972507181313544,
                    "contrast_ratio": 0.09694340869517198,
                    "duration": 53.70356349996291,
                    "success": true,
                    "additional_data": null
                },
                {
                    "sf": 3.617547501769875,
                    "contrast_ratio": 0.08088916621071751,
                    "duration": 54.40395609999541,
                    "success": true,
                    "additional_data": null
                },
                {
                    "sf": 4.678397200056396,
                    "contrast_ratio": 0.06749357484260758,
                    "duration": 57.60758039995562,
                    "success": true,
                    "additional_data": null
                },
                {
                    "sf": 6.050342214106982,
                    "contrast_ratio": 0.05631635061199455,
                    "duration": 64.81460120005067,
                    "success": false,
                    "additional_data": null
                }
            ]
        },
        {
            "key": 53.37668526468156,
            "trials": [
                {
                    "sf": 1.0,
                    "contrast_ratio": 0.2,
                    "duration": 2.552565500023775,
                    "success": true,
                    "additional_data": null
                },
                {
                    "sf": 1.1873231576444914,
                    "contrast_ratio": 0.1447197292187059,
                    "duration": 3.4365365999983624,
                    "success": true,
                    "additional_data": null
                },
                {
                    "sf": 1.409736280678886,
                    "contrast_ratio": 0.10471900012567781,
                    "duration": 5.722442000056617,
                    "success": true,
                    "additional_data": null
                },
                {
                    "sf": 1.673812532221656,
                    "contrast_ratio": 0.07577452671120863,
                    "duration": 7.590953900013119,
                    "success": true,
                    "additional_data": null
                },
                {
                    "sf": 1.9873563810623387,
                    "contrast_ratio": 0.054830344936608544,
                    "duration": 8.658674099948257,
                    "success": true,
                    "additional_data": null
                },
                {
                    "sf": 2.3596342537278647,
                    "contrast_ratio": 0.03967516336097116,
                    "duration": 9.926443099975586,
                    "success": true,
                    "additional_data": null
                },
                {
                    "sf": 2.8016483930222713,
                    "contrast_ratio": 0.028708894491538347,
                    "duration": 10.477076699957252,
                    "success": true,
                    "additional_data": null
                },
                {
                    "sf": 3.3264620166128185,
                    "contrast_ratio": 0.020773717184919133,
                    "duration": 11.094615699956194,
                    "success": true,
                    "additional_data": null
                },
                {
                    "sf": 3.9495853853491942,
                    "contrast_ratio": 0.015031833629337375,
                    "duration": 11.511316400021315,
                    "success": true,
                    "additional_data": null
                },
                {
                    "sf": 4.68943419111934,
                    "contrast_ratio": 0.010877014462491709,
                    "duration": 64.81460120005067,
                    "success": false,
                    "additional_data": null
                }
            ]
        },
        {
            "key": 80.06502789702235,
            "trials": [
                {
                    "sf": 1.0,
                    "contrast_ratio": 0.2,
                    "duration": 11.544822499970905,
                    "success": true,
                    "additional_data": null
                },
                {
                    "sf": 1.0509118634687664,
                    "contrast_ratio": 0.13445930159883876,
                    "duration": 11.961904699914157,
                    "success": true,
                    "additional_data": null
                },
                {
                    "sf": 1.1044157447793956,
                    "contrast_ratio": 0.0903965189322374,
                    "duration": 13.947301899897866,
                    "success": true,
                    "additional_data": null
                },
                {
                    "sf": 1.1606436083903604,
                    "contrast_ratio": 0.06077326401297422,
                    "duration": 15.66582719993312,
                    "success": true,
                    "additional_data": null
                },
                {
                    "sf": 1.219734137316627,
                    "contrast_ratio": 0.04085765317533177,
                    "duration": 17.500701699987985,
                    "success": true,
                    "additional_data": null
                },
                {
                    "sf": 1.281833075183885,
                    "contrast_ratio": 0.027468457554613437,
                    "duration": 18.218188099912368,
                    "success": true,
                    "additional_data": null
                },
                {
                    "sf": 1.3470935856973965,
                    "contrast_ratio": 0.018466948093953335,
                    "duration": 18.885459199897014,
                    "success": true,
                    "additional_data": null
                },
                {
                    "sf": 1.4156766304120734,
                    "contrast_ratio": 0.012415264716874862,
                    "duration": 19.686535599990748,
                    "success": true,
                    "additional_data": null
                },
                {
                    "sf": 1.4877513657355363,
                    "contrast_ratio": 0.00834673911497849,
                    "duration": 67.28393489995506,
                    "success": false,
                    "additional_data": null
                }
            ]
        },
        {
            "key": 106.75337052936312,
            "trials": [
                {
                    "sf": 1.0,
                    "contrast_ratio": 0.2,
                    "duration": 23.52323539997451,
                    "success": true,
                    "additional_data": null
                },
                {
                    "sf": 0.9203826540957304,
                    "contrast_ratio": 0.1359553594389355,
                    "duration": 24.891487499931827,
                    "success": true,
                    "additional_data": null
                },
                {
                    "sf": 0.8471042299603007,
                    "contrast_ratio": 0.09241929880085073,
                    "duration": 26.326361599960364,
                    "success": true,
                    "additional_data": null
                },
                {
                    "sf": 0.7796600394665815,
                    "contrast_ratio": 0.06282449493782019,
                    "duration": 28.328255499945953,
                    "success": true,
                    "additional_data": null
                },
                {
                    "sf": 0.7175855764166341,
                    "contrast_ratio": 0.04270663395420465,
                    "duration": 28.812018499942496,
                    "success": true,
                    "additional_data": null
                },
                {
                    "sf": 0.6604533173631563,
                    "contrast_ratio": 0.029030978848354694,
                    "duration": 29.229489199933596,
                    "success": true,
                    "additional_data": null
                },
                {
                    "sf": 0.6078697771410314,
                    "contrast_ratio": 0.019734585820960972,
                    "duration": 30.747550699976273,
                    "success": true,
                    "additional_data": null
                },
                {
                    "sf": 0.5594727988296426,
                    "contrast_ratio": 0.013415113543336344,
                    "duration": 31.781748099951074,
                    "success": true,
                    "additional_data": null
                },
                {
                    "sf": 0.514929059481193,
                    "contrast_ratio": 0.009119282918492124,
                    "duration": 34.968255699961446,
                    "success": true,
                    "additional_data": null
                },
                {
                    "sf": 0.4739317744363186,
                    "contrast_ratio": 0.006199076935044706,
                    "duration": 67.28393489995506,
                    "success": false,
                    "additional_data": null
                }
            ]
        },
        {
            "key": 53.37668526468156,
            "trials": [
                {
                    "sf": 1.0,
                    "contrast_ratio": 0.2,
                    "duration": 2.536123999976553,
                    "success": true,
                    "additional_data": null
                },
                {
                    "sf": 1.1873231576444914,
                    "contrast_ratio": 0.1447197292187059,
                    "duration": 3.2865527999820188,
                    "success": true,
                    "additional_data": null
                },
                {
                    "sf": 1.409736280678886,
                    "contrast_ratio": 0.10471900012567781,
                    "duration": 4.6880020999815315,
                    "success": true,
                    "additional_data": null
                },
                {
                    "sf": 1.673812532221656,
                    "contrast_ratio": 0.07577452671120863,
                    "duration": 5.538870599935763,
                    "success": true,
                    "additional_data": null
                },
                {
                    "sf": 1.9873563810623387,
                    "contrast_ratio": 0.054830344936608544,
                    "duration": 6.005996799911372,
                    "success": true,
                    "additional_data": null
                },
                {
                    "sf": 2.3596342537278647,
                    "contrast_ratio": 0.03967516336097116,
                    "duration": 7.090330999926664,
                    "success": true,
                    "additional_data": null
                },
                {
                    "sf": 2.8016483930222713,
                    "contrast_ratio": 0.028708894491538347,
                    "duration": 7.941478499909863,
                    "success": true,
                    "additional_data": null
                },
                {
                    "sf": 3.3264620166128185,
                    "contrast_ratio": 0.020773717184919133,
                    "duration": 67.28393489995506,
                    "success": false,
                    "additional_data": null
                }
            ]
        },
        {
            "key": 26.68834263234078,
            "trials": [
                {
                    "sf": 1.0,
                    "contrast_ratio": 0.2,
                    "duration": 52.285471899900585,
                    "success": true,
                    "additional_data": null
                },
                {
                    "sf": 1.2932510762519365,
                    "contrast_ratio": 0.1668791458840997,
                    "duration": 53.11993809998967,
                    "success": true,
                    "additional_data": null
                },
                {
                    "sf": 1.672498346226792,
                    "contrast_ratio": 0.13924324665503315,
                    "duration": 53.97038049995899,
                    "success": true,
                    "additional_data": null
                },
                {
                    "sf": 2.1629602862873822,
                    "contrast_ratio": 0.11618397035960476,
                    "duration": 57.57435789995361,
                    "success": true,
                    "additional_data": null
                },
                {
                    "sf": 2.7972507181313544,
                    "contrast_ratio": 0.09694340869517198,
                    "duration": 58.49173329991754,
                    "success": true,
                    "additional_data": null
                },
                {
                    "sf": 3.617547501769875,
                    "contrast_ratio": 0.08088916621071751,
                    "duration": 58.90896469994914,
                    "success": true,
                    "additional_data": null
                },
                {
                    "sf": 4.678397200056396,
                    "contrast_ratio": 0.06749357484260758,
                    "duration": 60.17676369997207,
                    "success": true,
                    "additional_data": null
                },
                {
                    "sf": 6.050342214106982,
                    "contrast_ratio": 0.05631635061199455,
                    "duration": 60.59391499997582,
                    "success": true,
                    "additional_data": null
                },
                {
                    "sf": 7.824611580086376,
                    "contrast_ratio": 0.04699012244719573,
                    "duration": 67.28393489995506,
                    "success": false,
                    "additional_data": null
                }
            ]
        },
        {
            "key": 0.0,
            "trials": [
                {
                    "sf": 1.0,
                    "contrast_ratio": 0.2,
                    "duration": 39.10585940000601,
                    "success": true,
                    "additional_data": null
                },
                {
                    "sf": 1.333521432163324,
                    "contrast_ratio": 0.2,
                    "duration": 39.77304209989961,
                    "success": true,
                    "additional_data": null
                },
                {
                    "sf": 1.7782794100389228,
                    "contrast_ratio": 0.2,
                    "duration": 40.857489299960434,
                    "success": true,
                    "additional_data": null
                },
                {
                    "sf": 2.3713737056616555,
                    "contrast_ratio": 0.2,
                    "duration": 41.84175989998039,
                    "success": true,
                    "additional_data": null
                },
                {
                    "sf": 3.16227766016838,
                    "contrast_ratio": 0.2,
                    "duration": 43.627138999989256,
                    "success": true,
                    "additional_data": null
                },
                {
                    "sf": 4.216965034285824,
                    "contrast_ratio": 0.2,
                    "duration": 44.44473089999519,
                    "success": true,
                    "additional_data": null
                },
                {
                    "sf": 5.623413251903492,
                    "contrast_ratio": 0.2,
                    "duration": 45.02854239998851,
                    "success": true,
                    "additional_data": null
                },
                {
                    "sf": 7.49894209332456,
                    "contrast_ratio": 0.2,
                    "duration": 47.914669599966146,
                    "success": true,
                    "additional_data": null
                },
                {
                    "sf": 10.000000000000004,
                    "contrast_ratio": 0.2,
                    "duration": 67.28393489995506,
                    "success": false,
                    "additional_data": null
                }
            ]
        },
        {
            "key": 0.0,
            "trials": [
                {
                    "sf": 1.0,
                    "contrast_ratio": 0.2,
                    "duration": 20.403825300047174,
                    "success": true,
                    "additional_data": null
                },
                {
                    "sf": 1.333521432163324,
                    "contrast_ratio": 0.2,
                    "duration": 21.187701600021683,
                    "success": true,
                    "additional_data": null
                },
                {
                    "sf": 1.7782794100389228,
                    "contrast_ratio": 0.2,
                    "duration": 22.9396486999467,
                    "success": true,
                    "additional_data": null
                },
                {
                    "sf": 2.3713737056616555,
                    "contrast_ratio": 0.2,
                    "duration": 23.69024809997063,
                    "success": true,
                    "additional_data": null
                },
                {
                    "sf": 3.16227766016838,
                    "contrast_ratio": 0.2,
                    "duration": 24.391152699943632,
                    "success": true,
                    "additional_data": null
                },
                {
                    "sf": 4.216965034285824,
                    "contrast_ratio": 0.2,
                    "duration": 25.091555000049993,
                    "success": true,
                    "additional_data": null
                },
                {
                    "sf": 5.623413251903492,
                    "contrast_ratio": 0.2,
                    "duration": 26.059303699992597,
                    "success": true,
                    "additional_data": null
                },
                {
                    "sf": 7.49894209332456,
                    "contrast_ratio": 0.2,
                    "duration": 27.610884099965915,
                    "success": true,
                    "additional_data": null
                },
                {
                    "sf": 10.000000000000004,
                    "contrast_ratio": 0.2,
                    "duration": 72.05545019998681,
                    "success": false,
                    "additional_data": null
                }
            ]
        },
        {
            "key": 53.37668526468156,
            "trials": [
                {
                    "sf": 1.0,
                    "contrast_ratio": 0.2,
                    "duration": 12.679233600036241,
                    "success": true,
                    "additional_data": null
                },
                {
                    "sf": 1.1873231576444914,
                    "contrast_ratio": 0.1447197292187059,
                    "duration": 13.096518700011075,
                    "success": true,
                    "additional_data": null
                },
                {
                    "sf": 1.409736280678886,
                    "contrast_ratio": 0.10471900012567781,
                    "duration": 14.013892199960537,
                    "success": true,
                    "additional_data": null
                },
                {
                    "sf": 1.673812532221656,
                    "contrast_ratio": 0.07577452671120863,
                    "duration": 14.697947600041516,
                    "success": true,
                    "additional_data": null
                },
                {
                    "sf": 1.9873563810623387,
                    "contrast_ratio": 0.054830344936608544,
                    "duration": 15.74923169997055,
                    "success": true,
                    "additional_data": null
                },
                {
                    "sf": 2.3596342537278647,
                    "contrast_ratio": 0.03967516336097116,
                    "duration": 17.116990700014867,
                    "success": true,
                    "additional_data": null
                },
                {
                    "sf": 2.8016483930222713,
                    "contrast_ratio": 0.028708894491538347,
                    "duration": 18.05125230003614,
                    "success": true,
                    "additional_data": null
                },
                {
                    "sf": 3.3264620166128185,
                    "contrast_ratio": 0.020773717184919133,
                    "duration": 18.635434999945574,
                    "success": true,
                    "additional_data": null
                },
                {
                    "sf": 3.9495853853491942,
                    "contrast_ratio": 0.015031833629337375,
                    "duration": 72.05545019998681,
                    "success": false,
                    "additional_data": null
                }
            ]
        },
        {
            "key": 106.75337052936312,
            "trials": [
                {
                    "sf": 1.0,
                    "contrast_ratio": 0.2,
                    "duration": 30.130167600000277,
                    "success": true,
                    "additional_data": null
                },
                {
                    "sf": 0.9203826540957304,
                    "contrast_ratio": 0.1359553594389355,
                    "duration": 30.730619800044224,
                    "success": true,
                    "additional_data": null
                },
                {
                    "sf": 0.8471042299603007,
                    "contrast_ratio": 0.09241929880085073,
                    "duration": 31.564763100002892,
                    "success": true,
                    "additional_data": null
                },
                {
                    "sf": 0.7796600394665815,
                    "contrast_ratio": 0.06282449493782019,
                    "duration": 32.71613570000045,
                    "success": true,
                    "additional_data": null
                },
                {
                    "sf": 0.7175855764166341,
                    "contrast_ratio": 0.04270663395420465,
                    "duration": 33.23335470003076,
                    "success": true,
                    "additional_data": null
                },
                {
                    "sf": 0.6604533173631563,
                    "contrast_ratio": 0.029030978848354694,
                    "duration": 36.65342750004493,
                    "success": true,
                    "additional_data": null
                },
                {
                    "sf": 0.6078697771410314,
                    "contrast_ratio": 0.019734585820960972,
                    "duration": 39.52292010001838,
                    "success": true,
                    "additional_data": null
                },
                {
                    "sf": 0.5594727988296426,
                    "contrast_ratio": 0.013415113543336344,
                    "duration": 57.273962300037965,
                    "success": true,
                    "additional_data": null
                },
                {
                    "sf": 0.514929059481193,
                    "contrast_ratio": 0.009119282918492124,
                    "duration": 58.77553430001717,
                    "success": true,
                    "additional_data": null
                },
                {
                    "sf": 0.4739317744363186,
                    "contrast_ratio": 0.006199076935044706,
                    "duration": 72.05545019998681,
                    "success": false,
                    "additional_data": null
                }
            ]
        },
        {
            "key": 26.68834263234078,
            "trials": [
                {
                    "sf": 1.0,
                    "contrast_ratio": 0.2,
                    "duration": 43.47668530000374,
                    "success": true,
                    "additional_data": null
                },
                {
                    "sf": 1.2932510762519365,
                    "contrast_ratio": 0.1668791458840997,
                    "duration": 45.445436500012875,
                    "success": true,
                    "additional_data": null
                },
                {
                    "sf": 1.672498346226792,
                    "contrast_ratio": 0.13924324665503315,
                    "duration": 46.413090700050816,
                    "success": true,
                    "additional_data": null
                },
                {
                    "sf": 2.1629602862873822,
                    "contrast_ratio": 0.11618397035960476,
                    "duration": 47.39726180001162,
                    "success": true,
                    "additional_data": null
                },
                {
                    "sf": 2.7972507181313544,
                    "contrast_ratio": 0.09694340869517198,
                    "duration": 47.93130159995053,
                    "success": true,
                    "additional_data": null
                },
                {
                    "sf": 3.617547501769875,
                    "contrast_ratio": 0.08088916621071751,
                    "duration": 48.64847290003672,
                    "success": true,
                    "additional_data": null
                },
                {
                    "sf": 4.678397200056396,
                    "contrast_ratio": 0.06749357484260758,
                    "duration": 49.06561419996433,
                    "success": true,
                    "additional_data": null
                },
                {
                    "sf": 6.050342214106982,
                    "contrast_ratio": 0.05631635061199455,
                    "duration": 72.05545019998681,
                    "success": false,
                    "additional_data": null
                }
            ]
        },
        {
            "key": 80.06502789702235,
            "trials": [
                {
                    "sf": 1.0,
                    "contrast_ratio": 0.2,
                    "duration": 2.952905199956149,
                    "success": true,
                    "additional_data": null
                },
                {
                    "sf": 1.0509118634687664,
                    "contrast_ratio": 0.13445930159883876,
                    "duration": 3.9870027999859303,
                    "success": true,
                    "additional_data": null
                },
                {
                    "sf": 1.1044157447793956,
                    "contrast_ratio": 0.0903965189322374,
                    "duration": 5.538792900042608,
                    "success": true,
                    "additional_data": null
                },
                {
                    "sf": 1.1606436083903604,
                    "contrast_ratio": 0.06077326401297422,
                    "duration": 6.072945500025526,
                    "success": true,
                    "additional_data": null
                },
                {
                    "sf": 1.219734137316627,
                    "contrast_ratio": 0.04085765317533177,
                    "duration": 6.590235100011341,
                    "success": true,
                    "additional_data": null
                },
                {
                    "sf": 1.281833075183885,
                    "contrast_ratio": 0.027468457554613437,
                    "duration": 8.892391699948348,
                    "success": true,
                    "additional_data": null
                },
                {
                    "sf": 1.3470935856973965,
                    "contrast_ratio": 0.018466948093953335,
                    "duration": 9.909810399985872,
                    "success": true,
                    "additional_data": null
                },
                {
                    "sf": 1.4156766304120734,
                    "contrast_ratio": 0.012415264716874862,
                    "duration": 10.543885700055398,
                    "success": true,
                    "additional_data": null
                },
                {
                    "sf": 1.4877513657355363,
                    "contrast_ratio": 0.00834673911497849,
                    "duration": 11.161337199970149,
                    "success": true,
                    "additional_data": null
                },
                {
                    "sf": 1.5634955601433351,
                    "contrast_ratio": 0.005611483560138585,
                    "duration": 72.05545019998681,
                    "success": false,
                    "additional_data": null
                }
            ]
        }
    ]
}